tosspayments_python_server_sdk-1.0.6.dist-info/licenses/LICENSE
tosspayments_server_sdk/__init__.py
tosspayments_server_sdk/auth.py
tosspayments_server_sdk/client.py
tosspayments_server_sdk/config.py
tosspayments_server_sdk/error_codes.py
tosspayments_server_sdk/exceptions.py
tosspayments_server_sdk/http_client.py
tosspayments_server_sdk/utils.py
tosspayments_server_sdk/models/__init__.py
tosspayments_server_sdk/models/base.py
tosspayments_server_sdk/models/enums.py
tosspayments_server_sdk/models/payment.py
tosspayments_server_sdk/models/webhook.py
tosspayments_server_sdk/resources/__init__.py
tosspayments_server_sdk/resources/base.py
tosspayments_server_sdk/resources/payments.py
tosspayments_server_sdk/resources/webhooks.py
tosspayments_python_server_sdk-1.0.6.dist-info/METADATA
tosspayments_python_server_sdk-1.0.6.dist-info/WHEEL
tosspayments_python_server_sdk-1.0.6.dist-info/top_level.txt
tosspayments_python_server_sdk-1.0.6.dist-info/RECORD
