Metadata-Version: 2.4
Name: tosspayments-python-server-sdk
Version: 1.0.6
Summary: Python SDK for TossPayments API - Simple and intuitive server-side payment processing
Author-email: Jayson Hwang <jhwang90801@gmail.com>
License-Expression: MIT
Project-URL: Homepage, https://github.com/jhwang0801/tosspayments-python-server-sdk
Project-URL: Documentation, https://jhwang0801.github.io/tosspayments-python-server-sdk/
Project-URL: Repository, https://github.com/jhwang0801/tosspayments-python-server-sdk.git
Project-URL: Bug Tracker, https://github.com/jhwang0801/tosspayments-python-server-sdk/issues
Keywords: tosspayments,payments,api,sdk,payment,fintech,korea,server
Classifier: Development Status :: 4 - Beta
Classifier: Intended Audience :: Developers
Classifier: Programming Language :: Python :: 3
Classifier: Programming Language :: Python :: 3.9
Classifier: Programming Language :: Python :: 3.10
Classifier: Programming Language :: Python :: 3.11
Classifier: Programming Language :: Python :: 3.12
Classifier: Topic :: Office/Business :: Financial
Classifier: Topic :: Internet :: WWW/HTTP
Classifier: Topic :: Software Development :: Libraries :: Python Modules
Requires-Python: >=3.9
License-File: LICENSE
Requires-Dist: requests>=2.28.0
Provides-Extra: dev
Requires-Dist: pytest>=7.0.0; extra == "dev"
Requires-Dist: pytest-cov>=4.0.0; extra == "dev"
Requires-Dist: pytest-mock>=3.10.0; extra == "dev"
Requires-Dist: black>=22.0.0; extra == "dev"
Requires-Dist: isort>=5.10.0; extra == "dev"
Requires-Dist: mypy>=1.0.0; extra == "dev"
Requires-Dist: flake8>=5.0.0; extra == "dev"
Dynamic: license-file
